dimtools/__init__.py
dimtools/cls_readconf.py
dimtools/fnc_mkdir.py
dimtools/fnc_readargs.py
dimtools/fnc_walker.py
dim_tools-3.0.1b0.dist-info/LICENSE
dim_tools-3.0.1b0.dist-info/METADATA
dim_tools-3.0.1b0.dist-info/WHEEL
dim_tools-3.0.1b0.dist-info/top_level.txt
dim_tools-3.0.1b0.dist-info/RECORD
