Metadata-Version: 2.1
Name: dim-tools
Version: 3.0.1b0
Summary: Useful python functions, the way I see them
Home-page: https://github.com/dmitiris/python-dim-tools
Author: Dmitry Pakalnis
Author-email: dmitry@unipat.ru
License: UNKNOWN
Platform: UNKNOWN
Classifier: Programming Language :: Python :: 3
Classifier: License :: OSI Approved :: Apache Software License
Classifier: Operating System :: OS Independent
